setup.py
Sew.egg-info/PKG-INFO
Sew.egg-info/SOURCES.txt
Sew.egg-info/dependency_links.txt
Sew.egg-info/top_level.txt
sew/__init__.py
sew/sew.py