Metadata-Version: 1.1
Name: Sew
Version: 1.0.0
Summary: Python threading tools
Home-page: https://github.com/coal0/sew
Author: UNKNOWN
Author-email: UNKNOWN
License: MIT
Keywords: sew,thread,threading
Platform: UNKNOWN
Classifier: Development Status :: 5 - Production/Stable
Classifier: License :: OSI Approved :: MIT License
Classifier: Programming Language :: Python :: 3
Classifier: Intended Audience :: Developers
Classifier: Topic :: Software Development
